Workbook

Sheet Control
A1: ILLUSTRATIVE — Workbook control
A3: ILLUSTRATIVE — replace all inputs with source-backed values before relying on any output.
A4: Purpose | B4: Formula-based reconciliation of the current AtlasRE acquisition case.
A5: Calculation | B5: Open in Excel or LibreOffice to recalculate live formulas before review.
A6: Model version | B6: deterministic-core-v0.10
A7: Run fingerprint | B7: 0ded2ea82bc0c0c27fb6ab5c14b7580eea437c81d3cd2aa54208570e0d79f861
A8: Source status | B8: REVIEW REQUIRED
A9: Workbook scope | B9: Acquisition underwriting only; no tax, refinancing, lease, or market-data model.

Sheet Inputs
A1: ILLUSTRATIVE — Inputs
A3: Input | B3: Workbook value | C3: Unit / note
A4: Purchase price | B4: 10000000 | C4: USD
A5: Annual NOI (year 1) | B5: 650000 | C5: USD / year
A6: Hold years | B6: 5 | C6: years
A7: Annual NOI growth | B7: 0.03 | C7: decimal
A8: Exit cap rate | B8: 0.06 | C8: decimal
A9: Discount rate | B9: 0.1 | C9: decimal
A10: Acquisition cost | B10: 0.03 | C10: decimal
A11: Selling cost | B11: 0.02 | C11: decimal
A12: Leverage | B12: 0.5 | C12: decimal
A13: Debt rate | B13: 0.06 | C13: decimal
A14: Debt amortization | B14: 20 | C14: years
A15: IRR hurdle | B15: 0.12 | C15: decimal; not a core model input
A16: Model version | B16: deterministic-core-v0.10 | C16: text
A17: Run fingerprint | B17: 0ded2ea82bc0c0c27fb6ab5c14b7580eea437c81d3cd2aa54208570e0d79f861 | C17: text
A18: Source status | B18: REVIEW REQUIRED | C18: ILLUSTRATIVE unless independently verified

Sheet Annual NOI
A1: ILLUSTRATIVE — Annual NOI and terminal value
A3: Year | B3: NOI | C3: Exit value | D3: Selling cost | E3: Unlevered operating CF | F3: Debt service | G3: DSCR
A4: 1 | B4: =Inputs!$B$5*(1+Inputs!$B$7)^(A4-1) | C4: =IF(A4=Inputs!$B$6,B4/Inputs!$B$8,0) | D4: =C4*Inputs!$B$11 | E4: =B4+C4-D4 | F4: =SUMIFS('Debt Schedule'!$F$4:$F$63,'Debt Schedule'!$B$4:$B$63,A4) | G4: =IF(F4=0,"",B4/F4)
A5: 2 | B5: =Inputs!$B$5*(1+Inputs!$B$7)^(A5-1) | C5: =IF(A5=Inputs!$B$6,B5/Inputs!$B$8,0) | D5: =C5*Inputs!$B$11 | E5: =B5+C5-D5 | F5: =SUMIFS('Debt Schedule'!$F$4:$F$63,'Debt Schedule'!$B$4:$B$63,A5) | G5: =IF(F5=0,"",B5/F5)
A6: 3 | B6: =Inputs!$B$5*(1+Inputs!$B$7)^(A6-1) | C6: =IF(A6=Inputs!$B$6,B6/Inputs!$B$8,0) | D6: =C6*Inputs!$B$11 | E6: =B6+C6-D6 | F6: =SUMIFS('Debt Schedule'!$F$4:$F$63,'Debt Schedule'!$B$4:$B$63,A6) | G6: =IF(F6=0,"",B6/F6)
A7: 4 | B7: =Inputs!$B$5*(1+Inputs!$B$7)^(A7-1) | C7: =IF(A7=Inputs!$B$6,B7/Inputs!$B$8,0) | D7: =C7*Inputs!$B$11 | E7: =B7+C7-D7 | F7: =SUMIFS('Debt Schedule'!$F$4:$F$63,'Debt Schedule'!$B$4:$B$63,A7) | G7: =IF(F7=0,"",B7/F7)
A8: 5 | B8: =Inputs!$B$5*(1+Inputs!$B$7)^(A8-1) | C8: =IF(A8=Inputs!$B$6,B8/Inputs!$B$8,0) | D8: =C8*Inputs!$B$11 | E8: =B8+C8-D8 | F8: =SUMIFS('Debt Schedule'!$F$4:$F$63,'Debt Schedule'!$B$4:$B$63,A8) | G8: =IF(F8=0,"",B8/F8)

Sheet Debt Schedule
A1: ILLUSTRATIVE — Monthly debt schedule
A3: Month | B3: Year | C3: Beginning balance | D3: Monthly rate | E3: Interest (IPMT) | F3: Payment (PMT) | G3: Principal (PPMT) | H3: Ending balance | I3: Balloon payoff | J3: Annual debt service
A4: 1 | B4: =ROUNDUP(A4/12,0) | C4: =Inputs!$B$4*Inputs!$B$12 | D4: =Inputs!$B$13/12 | E4: =-IPMT(D4,A4,Inputs!$B$14*12,Inputs!$B$4*Inputs!$B$12) | F4: =-PMT(D4,Inputs!$B$14*12,Inputs!$B$4*Inputs!$B$12) | G4: =-PPMT(D4,A4,Inputs!$B$14*12,Inputs!$B$4*Inputs!$B$12) | H4: =MAX(0,C4-G4) | I4: =IF(A4=Inputs!$B$6*12,H4,0) | J4: =SUMIFS($F$4:$F$63,$B$4:$B$63,B4)
A5: 2 | B5: =ROUNDUP(A5/12,0) | C5: =H4 | D5: =Inputs!$B$13/12 | E5: =-IPMT(D5,A5,Inputs!$B$14*12,Inputs!$B$4*Inputs!$B$12) | F5: =-PMT(D5,Inputs!$B$14*12,Inputs!$B$4*Inputs!$B$12) | G5: =-PPMT(D5,A5,Inputs!$B$14*12,Inputs!$B$4*Inputs!$B$12) | H5: =MAX(0,C5-G5) | I5: =IF(A5=Inputs!$B$6*12,H5,0) | J5: =SUMIFS($F$4:$F$63,$B$4:$B$63,B5)
A6: 3 | B6: =ROUNDUP(A6/12,0) | C6: =H5 | D6: =Inputs!$B$13/12 | E6: =-IPMT(D6,A6,Inputs!$B$14*12,Inputs!$B$4*Inputs!$B$12) | F6: =-PMT(D6,Inputs!$B$14*12,Inputs!$B$4*Inputs!$B$12) | G6: =-PPMT(D6,A6,Inputs!$B$14*12,Inputs!$B$4*Inputs!$B$12) | H6: =MAX(0,C6-G6) | I6: =IF(A6=Inputs!$B$6*12,H6,0) | J6: =SUMIFS($F$4:$F$63,$B$4:$B$63,B6)
A7: 4 | B7: =ROUNDUP(A7/12,0) | C7: =H6 | D7: =Inputs!$B$13/12 | E7: =-IPMT(D7,A7,Inputs!$B$14*12,Inputs!$B$4*Inputs!$B$12) | F7: =-PMT(D7,Inputs!$B$14*12,Inputs!$B$4*Inputs!$B$12) | G7: =-PPMT(D7,A7,Inputs!$B$14*12,Inputs!$B$4*Inputs!$B$12) | H7: =MAX(0,C7-G7) | I7: =IF(A7=Inputs!$B$6*12,H7,0) | J7: =SUMIFS($F$4:$F$63,$B$4:$B$63,B7)
A8: 5 | B8: =ROUNDUP(A8/12,0) | C8: =H7 | D8: =Inputs!$B$13/12 | E8: =-IPMT(D8,A8,Inputs!$B$14*12,Inputs!$B$4*Inputs!$B$12) | F8: =-PMT(D8,Inputs!$B$14*12,Inputs!$B$4*Inputs!$B$12) | G8: =-PPMT(D8,A8,Inputs!$B$14*12,Inputs!$B$4*Inputs!$B$12) | H8: =MAX(0,C8-G8) | I8: =IF(A8=Inputs!$B$6*12,H8,0) | J8: =SUMIFS($F$4:$F$63,$B$4:$B$63,B8)
A9: 6 | B9: =ROUNDUP(A9/12,0) | C9: =H8 | D9: =Inputs!$B$13/12 | E9: =-IPMT(D9,A9,Inputs!$B$14*12,Inputs!$B$4*Inputs!$B$12) | F9: =-PMT(D9,Inputs!$B$14*12,Inputs!$B$4*Inputs!$B$12) | G9: =-PPMT(D9,A9,Inputs!$B$14*12,Inputs!$B$4*Inputs!$B$12) | H9: =MAX(0,C9-G9) | I9: =IF(A9=Inputs!$B$6*12,H9,0) | J9: =SUMIFS($F$4:$F$63,$B$4:$B$63,B9)
A10: 7 | B10: =ROUNDUP(A10/12,0) | C10: =H9 | D10: =Inputs!$B$13/12 | E10: =-IPMT(D10,A10,Inputs!$B$14*12,Inputs!$B$4*Inputs!$B$12) | F10: =-PMT(D10,Inputs!$B$14*12,Inputs!$B$4*Inputs!$B$12) | G10: =-PPMT(D10,A10,Inputs!$B$14*12,Inputs!$B$4*Inputs!$B$12) | H10: =MAX(0,C10-G10) | I10: =IF(A10=Inputs!$B$6*12,H10,0) | J10: =SUMIFS($F$4:$F$63,$B$4:$B$63,B10)
A11: 8 | B11: =ROUNDUP(A11/12,0) | C11: =H10 | D11: =Inputs!$B$13/12 | E11: =-IPMT(D11,A11,Inputs!$B$14*12,Inputs!$B$4*Inputs!$B$12) | F11: =-PMT(D11,Inputs!$B$14*12,Inputs!$B$4*Inputs!$B$12) | G11: =-PPMT(D11,A11,Inputs!$B$14*12,Inputs!$B$4*Inputs!$B$12) | H11: =MAX(0,C11-G11) | I11: =IF(A11=Inputs!$B$6*12,H11,0) | J11: =SUMIFS($F$4:$F$63,$B$4:$B$63,B11)
A12: 9 | B12: =ROUNDUP(A12/12,0) | C12: =H11 | D12: =Inputs!$B$13/12 | E12: =-IPMT(D12,A12,Inputs!$B$14*12,Inputs!$B$4*Inputs!$B$12) | F12: =-PMT(D12,Inputs!$B$14*12,Inputs!$B$4*Inputs!$B$12) | G12: =-PPMT(D12,A12,Inputs!$B$14*12,Inputs!$B$4*Inputs!$B$12) | H12: =MAX(0,C12-G12) | I12: =IF(A12=Inputs!$B$6*12,H12,0) | J12: =SUMIFS($F$4:$F$63,$B$4:$B$63,B12)
A13: 10 | B13: =ROUNDUP(A13/12,0) | C13: =H12 | D13: =Inputs!$B$13/12 | E13: =-IPMT(D13,A13,Inputs!$B$14*12,Inputs!$B$4*Inputs!$B$12) | F13: =-PMT(D13,Inputs!$B$14*12,Inputs!$B$4*Inputs!$B$12) | G13: =-PPMT(D13,A13,Inputs!$B$14*12,Inputs!$B$4*Inputs!$B$12) | H13: =MAX(0,C13-G13) | I13: =IF(A13=Inputs!$B$6*12,H13,0) | J13: =SUMIFS($F$4:$F$63,$B$4:$B$63,B13)
A14: 11 | B14: =ROUNDUP(A14/12,0) | C14: =H13 | D14: =Inputs!$B$13/12 | E14: =-IPMT(D14,A14,Inputs!$B$14*12,Inputs!$B$4*Inputs!$B$12) | F14: =-PMT(D14,Inputs!$B$14*12,Inputs!$B$4*Inputs!$B$12) | G14: =-PPMT(D14,A14,Inputs!$B$14*12,Inputs!$B$4*Inputs!$B$12) | H14: =MAX(0,C14-G14) | I14: =IF(A14=Inputs!$B$6*12,H14,0) | J14: =SUMIFS($F$4:$F$63,$B$4:$B$63,B14)
A15: 12 | B15: =ROUNDUP(A15/12,0) | C15: =H14 | D15: =Inputs!$B$13/12 | E15: =-IPMT(D15,A15,Inputs!$B$14*12,Inputs!$B$4*Inputs!$B$12) | F15: =-PMT(D15,Inputs!$B$14*12,Inputs!$B$4*Inputs!$B$12) | G15: =-PPMT(D15,A15,Inputs!$B$14*12,Inputs!$B$4*Inputs!$B$12) | H15: =MAX(0,C15-G15) | I15: =IF(A15=Inputs!$B$6*12,H15,0) | J15: =SUMIFS($F$4:$F$63,$B$4:$B$63,B15)
A16: 13 | B16: =ROUNDUP(A16/12,0) | C16: =H15 | D16: =Inputs!$B$13/12 | E16: =-IPMT(D16,A16,Inputs!$B$14*12,Inputs!$B$4*Inputs!$B$12) | F16: =-PMT(D16,Inputs!$B$14*12,Inputs!$B$4*Inputs!$B$12) | G16: =-PPMT(D16,A16,Inputs!$B$14*12,Inputs!$B$4*Inputs!$B$12) | H16: =MAX(0,C16-G16) | I16: =IF(A16=Inputs!$B$6*12,H16,0) | J16: =SUMIFS($F$4:$F$63,$B$4:$B$63,B16)
... A63: 60 | B63: =ROUNDUP(A63/12,0) | C63: =H62 | D63: =Inputs!$B$13/12 | E63: =-IPMT(D63,A63,Inputs!$B$14*12,Inputs!$B$4*Inputs!$B$12) | F63: =-PMT(D63,Inputs!$B$14*12,Inputs!$B$4*Inputs!$B$12) | G63: =-PPMT(D63,A63,Inputs!$B$14*12,Inputs!$B$4*Inputs!$B$12) | H63: =MAX(0,C63-G63) | I63: =IF(A63=Inputs!$B$6*12,H63,0) | J63: =SUMIFS($F$4:$F$63,$B$4:$B$63,B63)

Sheet Cash Flows
A1: ILLUSTRATIVE — Annual levered and unlevered cash flows
A3: Period | B3: Unlevered cash flow | C3: Levered cash flow | D3: Detail
A4: 0 | B4: =-Inputs!$B$4*(1+Inputs!$B$10) | C4: =B4+Inputs!$B$4*Inputs!$B$12 | D4: Acquisition and initial equity
A5: 1 | B5: ='Annual NOI'!E4 | C5: =B5-'Annual NOI'!F4 | D5: Year 1
A6: 2 | B6: ='Annual NOI'!E5 | C6: =B6-'Annual NOI'!F5 | D6: Year 2
A7: 3 | B7: ='Annual NOI'!E6 | C7: =B7-'Annual NOI'!F6 | D7: Year 3
A8: 4 | B8: ='Annual NOI'!E7 | C8: =B8-'Annual NOI'!F7 | D8: Year 4
A9: 5 | B9: ='Annual NOI'!E8 | C9: =B9-'Annual NOI'!F8-'Debt Schedule'!I63 | D9: Year 5
A11: Unlevered IRR | B11: =IRR(B4:B9)
A12: Levered IRR | B12: =IRR(C4:C9)
A13: Unlevered NPV | B13: =B4+NPV(Inputs!$B$9,B5:B9)
A14: Equity multiple | B14: =SUMIF(C4:C9,">0",C4:C9)/-SUMIF(C4:C9,"<0",C4:C9)

Sheet Reconciliation
A1: ILLUSTRATIVE — Formula-to-model reconciliation
A2: Difference is workbook formula less static Python model output. Amounts should be approximately zero after recalculation.
A3: Metric | B3: Excel formula result | C3: Model output | D3: Difference | E3: Tolerance | F3: Status
A4: Entry cap rate | B4: =Inputs!$B$5/Inputs!$B$4 | C4: 0.065 | D4: =B4-C4 | E4: 1e-08 | F4: =IF(ABS(D4)<=E4,"PASS","REVIEW")
A5: Exit value | B5: ='Annual NOI'!C8 | C5: 12193012 | D5: =B5-C5 | E5: 0.01 | F5: =IF(ABS(D5)<=E5,"PASS","REVIEW")
A6: Remaining debt at exit | B6: ='Debt Schedule'!H63 | C6: 4244979.9 | D6: =B6-C6 | E6: 0.01 | F6: =IF(ABS(D6)<=E6,"PASS","REVIEW")
A7: Minimum DSCR | B7: =MIN('Annual NOI'!G4:G8) | C7: 1.512125 | D7: =B7-C7 | E7: 1e-08 | F7: =IF(ABS(D7)<=E7,"PASS","REVIEW")
A8: Unlevered IRR | B8: ='Cash Flows'!B11 | C8: 0.093238471 | D8: =B8-C8 | E8: 1e-08 | F8: =IF(ABS(D8)<=E8,"PASS","REVIEW")
A9: Levered IRR | B9: ='Cash Flows'!B12 | C9: 0.11970066 | D9: =B9-C9 | E9: 1e-08 | F9: =IF(ABS(D9)<=E9,"PASS","REVIEW")
A10: Unlevered NPV | B10: ='Cash Flows'!B13 | C10: -278826.74 | D10: =B10-C10 | E10: 0.01 | F10: =IF(ABS(D10)<=E10,"PASS","REVIEW")
A11: Equity multiple | B11: ='Cash Flows'!B14 | C11: 1.6992108 | D11: =B11-C11 | E11: 1e-08 | F11: =IF(ABS(D11)<=E11,"PASS","REVIEW")

Sheet Lineage
A1: ILLUSTRATIVE — Assumption and lineage register
A3: assumption_id | B3: name | C3: value | D3: unit | E3: version | F3: source | G3: status | H3: owner | I3: verified_by | J3: effective_at | K3: supersedes | L3: notes
A4: ATLAS-001:purchase_price:v1 | B4: purchase_price | C4: 10000000 | D4: USD | E4: 1 | F4: Illustrative reconciliation workbook | G4: REVIEW REQUIRED | H4: Investment team
A5: ATLAS-001:annual_noi:v1 | B5: annual_noi | C5: 650000 | D5: USD / year | E5: 1 | F5: Illustrative reconciliation workbook | G5: REVIEW REQUIRED | H5: Investment team
A6: ATLAS-001:annual_noi_growth:v1 | B6: annual_noi_growth | C6: 0.03 | D6: % | E6: 1 | F6: Illustrative reconciliation workbook | G6: REVIEW REQUIRED | H6: Investment team
A7: ATLAS-001:exit_cap_rate:v1 | B7: exit_cap_rate | C7: 0.06 | D7: % | E7: 1 | F7: Illustrative reconciliation workbook | G7: REVIEW REQUIRED | H7: Investment team
A8: ATLAS-001:discount_rate:v1 | B8: discount_rate | C8: 0.1 | D8: % | E8: 1 | F8: Illustrative reconciliation workbook | G8: REVIEW REQUIRED | H8: Investment team
A9: ATLAS-001:acquisition_cost_pct:v1 | B9: acquisition_cost_pct | C9: 0.03 | D9: % | E9: 1 | F9: Illustrative reconciliation workbook | G9: REVIEW REQUIRED | H9: Investment team
A10: ATLAS-001:selling_cost_pct:v1 | B10: selling_cost_pct | C10: 0.02 | D10: % | E10: 1 | F10: Illustrative reconciliation workbook | G10: REVIEW REQUIRED | H10: Investment team
A11: ATLAS-001:leverage:v1 | B11: leverage | C11: 0.5 | D11: % | E11: 1 | F11: Illustrative reconciliation workbook | G11: REVIEW REQUIRED | H11: Investment team
A12: ATLAS-001:debt_rate:v1 | B12: debt_rate | C12: 0.06 | D12: % | E12: 1 | F12: Illustrative reconciliation workbook | G12: REVIEW REQUIRED | H12: Investment team
A13: ATLAS-001:debt_amortization_years:v1 | B13: debt_amortization_years | C13: 20 | D13: years | E13: 1 | F13: Illustrative reconciliation workbook | G13: REVIEW REQUIRED | H13: Investment team
A14: ATLAS-001:irr_hurdle:v1 | B14: irr_hurdle | C14: 0.12 | D14: % | E14: 1 | F14: Illustrative reconciliation workbook | G14: REVIEW REQUIRED | H14: Investment team
A17: Lineage records
A18: Output | B18: Value | C18: Inputs | D18: Method | E18: Source references | F18: Assumption version
A19: levered_irr | B19: derived | C19: purchase_price, annual_noi, annual_noi_growth, exit_cap_rate, leverage | D19: annual debt schedule + equity cash-flow IRR | E19: deal_inputs.csv | F19: 1
A20: minimum_dscr | B20: derived | C20: annual_noi, debt_rate, debt_amortization_years, leverage | D20: annual NOI / annual debt service | E20: loan_terms.xlsx | F20: 1
A21: exit_value | B21: derived | C21: annual_noi, annual_noi_growth, exit_cap_rate | D21: forward NOI / exit cap rate | E21: market_comps.pdf | F21: 1
